libyear/__about__.py
libyear/__init__.py
libyear/main.py
libyear/pypi.py
libyear/results.py
libyear/toml.py
libyear/utils.py
pylibyear-0.3.4.dist-info/LICENSE
pylibyear-0.3.4.dist-info/METADATA
pylibyear-0.3.4.dist-info/WHEEL
pylibyear-0.3.4.dist-info/entry_points.txt
pylibyear-0.3.4.dist-info/top_level.txt
pylibyear-0.3.4.dist-info/RECORD
