Metadata-Version: 2.1
Name: pylibyear
Version: 0.3.4
Summary: A simple measure of software dependency freshness.
Author: nasirhjafri
Author-email: Sam Atkins <samatkins@outlook.com>
License: MIT License
Project-URL: Documentation, https://github.com/sam-atkins/pylibyear#readme
Project-URL: Issues, https://github.com/sam-atkins/pylibyear/issues
Project-URL: Source, https://github.com/sam-atkins/pylibyear
Classifier: Programming Language :: Python
Classifier: Programming Language :: Python :: 3.11
Classifier: Programming Language :: Python :: 3.12
Classifier: Programming Language :: Python :: Implementation :: PyPy
Requires-Python: >=3.11
License-File: LICENSE
Requires-Dist: requests >=2.31.0
Requires-Dist: packaging >=24.0
Requires-Dist: prettytable >=3.10.0
Requires-Dist: python-dateutil >=2.9.0.post0
Requires-Dist: typer >=0.12.3
Provides-Extra: build
Requires-Dist: build ==1.2.1 ; extra == 'build'
Provides-Extra: dev
Requires-Dist: pytest >=8.2.0 ; extra == 'dev'
Requires-Dist: pytest-vcr >=1.0.2 ; extra == 'dev'
Requires-Dist: ruff >=0.4.4 ; extra == 'dev'
